pytruststore/__init__.py
pytruststore/__main__.py
pytruststore/alias.py
pytruststore/cli_wrapper.py
pytruststore/keystore.py
pytruststore/logging_config.py
pytruststore/utils.py
pytruststore/validation.py
pytruststore-0.1.1.dist-info/METADATA
pytruststore-0.1.1.dist-info/WHEEL
pytruststore-0.1.1.dist-info/entry_points.txt
pytruststore-0.1.1.dist-info/licenses/LICENSE
pytruststore-0.1.1.dist-info/RECORD
