Metadata-Version: 2.4
Name: pytruststore
Version: 0.1.1
Summary: A Python application for working with Java keystore files
Author: GLIC Team
License: Apache-2.0
License-File: LICENSE
Requires-Python: >=3.8
Requires-Dist: click>=8.1.0
Requires-Dist: cryptography>=41.0.0
Requires-Dist: pyjks>=20.0.0
Requires-Dist: rich>=13.0.0
Requires-Dist: structlog>=23.0.0
Provides-Extra: dev
Requires-Dist: pytest>=7.0.0; extra == 'dev'
Requires-Dist: ruff>=0.0.270; extra == 'dev'
